Metadata-Version: 2.1
Name: quickpiggy
Version: 0.3.0
Summary: QuickPiggy - launch an impromptu PostgreSQL server, hassle free.
Home-page: https://github.com/blinkingtwelve/quickpiggy
Author: nullenenenen
Author-email: nullenenenen@gavagai.eu
License: Unlicense
Keywords: postgresql
Platform: UNKNOWN
Classifier: Development Status :: 4 - Beta
Classifier: Environment :: Other Environment
Classifier: Intended Audience :: Developers
Classifier: License :: OSI Approved :: The Unlicense (Unlicense)
Classifier: Operating System :: POSIX
Classifier: Topic :: Software Development :: Libraries :: Python Modules
Classifier: Topic :: Database
Classifier: Programming Language :: Python
Classifier: Programming Language :: Python :: 2.7
Classifier: Programming Language :: Python :: 3
Requires-Python: !=3.0.*,>=2.7
